gpamstfdigital/__init__.py
gpamstfdigital/configserver.py
gpamstfdigital/discovery.py
gpamstfdigital/logger.py
gpamstfdigital/rmq.py
gpam_stfdigital-186963947.dist-info/METADATA
gpam_stfdigital-186963947.dist-info/WHEEL
gpam_stfdigital-186963947.dist-info/top_level.txt
gpam_stfdigital-186963947.dist-info/RECORD
