Metadata-Version: 2.1
Name: gpam-stfdigital
Version: 186963947
Summary: Client for integrate service with STF Digital
Home-page: https://supremotribunalfederal.gitlab.io/
Author: GPAM
Author-email: gpamunb@gmail.com
License: MIT
Platform: UNKNOWN
Requires-Dist: pika
Requires-Dist: requests
Requires-Dist: python-consul
